magicapi/Decorators/__init__.py
magicapi/Decorators/background_tasks.py
magicapi/Decorators/firestore.py
magicapi/Decorators/helpers.py
magicapi/Decorators/parse_objects.py
magicapi/Decorators/time.py
magicapi/Errors/MagicExceptions.py
magicapi/Errors/__init__.py
magicapi/FieldTypes/PhoneNumber.py
magicapi/FieldTypes/__init__.py
magicapi/Globals/G.py
magicapi/Globals/__init__.py
magicapi/Models/BackgroundTask.py
magicapi/Models/Call.py
magicapi/Models/NotFound.py
magicapi/Models/Task.py
magicapi/Models/__init__.py
magicapi/Models/task_executor.py
magicapi/RouteClasses/__init__.py
magicapi/RouteClasses/middleware.py
magicapi/Services/Doorman/CurrentUser.py
magicapi/Services/Doorman/__init__.py
magicapi/Services/Doorman/errors.py
magicapi/Services/Email/__init__.py
magicapi/Services/MagicLink/__init__.py
magicapi/Services/MagicLink/template.py
magicapi/Services/Mailgun/__init__.py
magicapi/Services/Segment/__init__.py
magicapi/Services/Segment/decorator.py
magicapi/Services/Sentry/__init__.py
magicapi/Services/Stripe/__init__.py
magicapi/Services/Twilio/__init__.py
magicapi/Services/__init__.py
magicapi/Utils/__init__.py
magicapi/Utils/importing.py
magicapi/Utils/random_utils.py
magicapi/__init__.py
magicapi/app_factory.py
magicapi/cli.py
magicapi/config.py
magicapi-0.1.147.dist-info/entry_points.txt
magicapi-0.1.147.dist-info/WHEEL
magicapi-0.1.147.dist-info/METADATA
magicapi-0.1.147.dist-info/RECORD
