Metadata-Version: 2.1
Name: magicapi
Version: 0.1.147
Summary: 
Home-page: https://github.com/jerber/MagicAPI
Author: Jeremy Berman
Author-email: jerber@sas.upenn.edu
Requires-Python: >=3.8,<4.0
Classifier: Programming Language :: Python :: 3
Classifier: Programming Language :: Python :: 3.10
Classifier: Programming Language :: Python :: 3.8
Classifier: Programming Language :: Python :: 3.9
Requires-Dist: analytics-python (>=1.2.9,<2.0.0)
Requires-Dist: boto3 (>=1.14.23,<2.0.0)
Requires-Dist: fastapi[all] (>=0.63.0,<0.64.0)
Requires-Dist: magicdb (>=0.2.139,<0.3.0)
Requires-Dist: mangum (>=0.9.2,<0.10.0)
Requires-Dist: phonenumbers (>=8.12.6,<9.0.0)
Requires-Dist: pydantic[dotenv] (>=1.7.3,<2.0.0)
Requires-Dist: requests (>=2.24.0,<3.0.0)
Requires-Dist: sentry-sdk (>=0.19.4,<0.20.0)
Requires-Dist: stripe (>=2.49.0,<3.0.0)
Requires-Dist: twilio (>=6.44.0,<7.0.0)
Requires-Dist: typer (>=0.3.1,<0.4.0)
Project-URL: Repository, https://github.com/jerber/MagicAPI
